.gitignore
LICENSE
MANIFEST.in
README.md
build_dists.py
make_test_files.sh
minimal.hu
pretty.hu
pyproject.toml
requirements.txt
setup.py
subprocess
test.sh
clib/humon/include/humon/ansiColors.h
clib/humon/include/humon/humon.h
clib/humon/include/humon/version.h
clib/humon/src/ansiColors.c
clib/humon/src/changes.c
clib/humon/src/encoding.c
clib/humon/src/humon.internal.h
clib/humon/src/node.c
clib/humon/src/parse.c
clib/humon/src/printing.c
clib/humon/src/token.c
clib/humon/src/tokenize.c
clib/humon/src/trove.c
clib/humon/src/utils.c
clib/humon/src/vector.c
src/humon/_version.py
src/humon/chumon.pxd
src/humon/humon.c
src/humon/humon.pyx
src/humon.egg-info/PKG-INFO
src/humon.egg-info/SOURCES.txt
src/humon.egg-info/dependency_links.txt
src/humon.egg-info/top_level.txt
tests/__init__.py
tests/comment-only-pc-ca.hu
tests/comment-only-pc-cn.hu
tests/comment-only-pm-ca.hu
tests/comment-only-pm-cn.hu
tests/comment-only-pp-ca.hu
tests/comment-only-pp-cn.hu
tests/dict-only-pc-ca.hu
tests/dict-only-pc-cn.hu
tests/dict-only-pm-ca.hu
tests/dict-only-pm-cn.hu
tests/dict-only-pp-ca.hu
tests/dict-only-pp-cn.hu
tests/foo.hu
tests/gnome-pc-ca.hu
tests/gnome-pc-cn.hu
tests/gnome-pm-ca.hu
tests/gnome-pm-cn.hu
tests/gnome-pp-ca.hu
tests/gnome-pp-cn.hu
tests/gnome.hu
tests/inane-pc-ca.hu
tests/inane-pc-cn.hu
tests/inane-pm-ca.hu
tests/inane-pm-cn.hu
tests/inane-pp-ca.hu
tests/inane-pp-cn.hu
tests/list-only-pc-ca.hu
tests/list-only-pc-cn.hu
tests/list-only-pm-ca.hu
tests/list-only-pm-cn.hu
tests/list-only-pp-ca.hu
tests/list-only-pp-cn.hu
tests/metatag-only-pc-ca.hu
tests/metatag-only-pc-cn.hu
tests/metatag-only-pm-ca.hu
tests/metatag-only-pm-cn.hu
tests/metatag-only-pp-ca.hu
tests/metatag-only-pp-cn.hu
tests/test_from_api.py
tests/test_node_api.py
tests/test_trove_api.py
tests/value-only-pc-ca.hu
tests/value-only-pc-cn.hu
tests/value-only-pm-ca.hu
tests/value-only-pm-cn.hu
tests/value-only-pp-ca.hu
tests/value-only-pp-cn.hu
tests/test_output/comment_only.hu
tests/test_output/dict_only.hu
tests/test_output/gnome.hu
tests/test_output/inane.hu
tests/test_output/list_only.hu
tests/test_output/metatag_only.hu
