Metadata-Version: 2.1
Name: humon
Version: 0.1.0
Summary: A python wrapper for the Humon C API.
Author-email: Trevor Schrock <spacemeat@gmail.com>
Maintainer-email: Trevor Schrock <spacemeat@gmail.com>
License: MIT License
Project-URL: Repository, https://github.com/spacemeat/humon-cy.git
Keywords: Humon,C
Classifier: Development Status :: 3 - Alpha
Classifier: Intended Audience :: Developers
Classifier: Programming Language :: Python :: 3.10
Classifier: Programming Language :: C
Classifier: Programming Language :: Cython
Classifier: License :: OSI Approved :: MIT License
Classifier: Programming Language :: Python :: Implementation :: CPython
Requires-Python: >=3.10
License-File: LICENSE
